LICENSE.GPL
LICENSE.txt
setup.cfg
setup.py
iscorpio/__init__.py
iscorpio.themes.redmaple.egg-info/PKG-INFO
iscorpio.themes.redmaple.egg-info/SOURCES.txt
iscorpio.themes.redmaple.egg-info/dependency_links.txt
iscorpio.themes.redmaple.egg-info/entry_points.txt
iscorpio.themes.redmaple.egg-info/namespace_packages.txt
iscorpio.themes.redmaple.egg-info/not-zip-safe
iscorpio.themes.redmaple.egg-info/requires.txt
iscorpio.themes.redmaple.egg-info/top_level.txt
iscorpio/themes/__init__.py
iscorpio/themes/redmaple/HISTORY.txt
iscorpio/themes/redmaple/README.txt
iscorpio/themes/redmaple/__init__.py
iscorpio/themes/redmaple/configure.zcml
iscorpio/themes/redmaple/profiles.zcml
iscorpio/themes/redmaple/skins.zcml
iscorpio/themes/redmaple/version.txt
iscorpio/themes/redmaple/Extensions/Install.py
iscorpio/themes/redmaple/profiles/default/cssregistry.xml
iscorpio/themes/redmaple/profiles/default/import_steps.xml
iscorpio/themes/redmaple/profiles/default/metadata.xml
iscorpio/themes/redmaple/profiles/default/redmaple_various.txt
iscorpio/themes/redmaple/profiles/default/skins.xml
iscorpio/themes/redmaple/profiles/uninstall/skins.xml
iscorpio/themes/redmaple/skins/iscorpio_redmaple_styles/base_properties.props
iscorpio/themes/redmaple/skins/iscorpio_redmaple_styles/iscorpioRedmaple.css.dtml