Metadata-Version: 1.0
Name: iscorpio.themes.redmaple
Version: 0.1
Summary: iscorpio readmaple Plone 3 theme
Home-page: http://plonexp.leocorn.com/plonepm
Author: Sean Chen
Author-email: sean.chen@leocorn.com
License: GPL
Keywords: Zope Plone Python Theme Web
Platform: UNKNOWN
Classifier: Development Status :: 5 - Production/Stable
Classifier: Environment :: Web Environment
Classifier: Framework :: Plone
Classifier: License :: OSI Approved :: GNU General Public License (GPL)
Classifier: Programming Language :: Python
Classifier: Programming Language :: Zope
Classifier: Topic :: Software Development :: Libraries :: Python Modules
